pyssm_client/__init__.py
pyssm_client/constants.py
pyssm_client/exec.py
pyssm_client/cli/__init__.py
pyssm_client/cli/coordinator.py
pyssm_client/cli/main.py
pyssm_client/cli/types.py
pyssm_client/communicator/__init__.py
pyssm_client/communicator/data_channel.py
pyssm_client/communicator/message_handlers.py
pyssm_client/communicator/message_parser.py
pyssm_client/communicator/protocol.py
pyssm_client/communicator/types.py
pyssm_client/communicator/utils.py
pyssm_client/communicator/websocket_channel.py
pyssm_client/file_transfer/__init__.py
pyssm_client/file_transfer/client.py
pyssm_client/file_transfer/types.py
pyssm_client/session/__init__.py
pyssm_client/session/protocols.py
pyssm_client/session/registry.py
pyssm_client/session/session.py
pyssm_client/session/session_handler.py
pyssm_client/session/types.py
pyssm_client/session/plugins/__init__.py
pyssm_client/session/plugins/base.py
pyssm_client/session/plugins/file_transfer.py
pyssm_client/session/plugins/interactive_commands.py
pyssm_client/session/plugins/port.py
pyssm_client/session/plugins/standard_stream.py
pyssm_client/session/plugins/utils.py
pyssm_client/utils/__init__.py
pyssm_client/utils/command.py
pyssm_client/utils/logging.py
pyssm_client-0.1.1.dist-info/METADATA
pyssm_client-0.1.1.dist-info/WHEEL
pyssm_client-0.1.1.dist-info/entry_points.txt
pyssm_client-0.1.1.dist-info/licenses/LICENSE
pyssm_client-0.1.1.dist-info/RECORD
