Metadata-Version: 2.4
Name: pyssm-client
Version: 0.1.1
Summary: Enhanced Python AWS SSM Session Manager client with interactive sessions, exec, and file transfer support
Author-email: Damon Cortesi <d.lifehacker@gmail.com>
License: Apache-2.0
License-File: LICENSE
Keywords: aws,ec2,session-manager,ssh,ssm
Classifier: Development Status :: 4 - Beta
Classifier: Intended Audience :: Developers
Classifier: Intended Audience :: System Administrators
Classifier: License :: OSI Approved :: Apache Software License
Classifier: Programming Language :: Python :: 3
Classifier: Programming Language :: Python :: 3.12
Classifier: Programming Language :: Python :: 3.13
Classifier: Topic :: Internet :: WWW/HTTP
Classifier: Topic :: Software Development :: Libraries :: Python Modules
Classifier: Topic :: System :: Systems Administration
Requires-Python: >=3.12
Requires-Dist: boto3>=1.34.0
Requires-Dist: click>=8.1.0
Requires-Dist: websockets>=15.0.1
